[
  {
    "icon": "Blog",
    "name": "博客",
    "link": "https://gogoup.de/"
  },
  {
    "icon": "AirplanemodeActiveFilled",
    "name": "探针",
    "link": "https://tz.360361.xyz/"
  },
  {
    "icon": "AirplaneOutline",
    "name": "NEZHA DASH",
    "link": "https://tz.gogoup.de/"
  },
  {
    "icon": "PictureOutlined",
    "name": "图床",
    "link": "https://pic.360361.xyz/"
  },
  {
    "icon": "AttachFileFilled",
    "name": "文件小站",
    "link": "https://file.360361.xyz/"
  },
  {
    "icon": "FireOutlined",
    "name": "今日热榜",
    "link": "https://hot.imsyy.top/"
  }
]
